print_utilities
