Metadata-Version: 2.1
Name: print-utilities
Version: 0.0.2
Summary: Uma biblioteca com varias utilidades para printar
Home-page: UNKNOWN
Author: CarlosAllberto
Author-email: dasilvacarlosalberto344@gmail.com
License: MIT License
Keywords: print utilities
Platform: UNKNOWN
License-File: LICENSE
